mcp_server_aibtcdev/__init__.py
mcp_server_aibtcdev/main.py
mcp_server_aibtcdev/server.py
mcp_server_aibtcdev/settings.py
mcp_server_aibtcdev/tools.py
mcp_server_aibtcdev-1.0.0.dist-info/METADATA
mcp_server_aibtcdev-1.0.0.dist-info/WHEEL
mcp_server_aibtcdev-1.0.0.dist-info/entry_points.txt
mcp_server_aibtcdev-1.0.0.dist-info/licenses/LICENSE
mcp_server_aibtcdev-1.0.0.dist-info/RECORD
