Metadata-Version: 2.4
Name: mcp-server-aibtcdev
Version: 1.0.0
Summary: MCP server for aibtcdev-backend API integration
License-Expression: Apache-2.0
License-File: LICENSE
Requires-Python: >=3.13
Requires-Dist: fastmcp>=2.7.0
Requires-Dist: httpx>=0.26.1
Requires-Dist: pydantic>=2.10.6
Requires-Dist: typing-extensions>=4.0.0
